skelform_python/__init__.py
skelform_python/tests.py
skelform_python-0.2.1.dist-info/METADATA
skelform_python-0.2.1.dist-info/WHEEL
skelform_python-0.2.1.dist-info/RECORD
