Metadata-Version: 2.4
Name: skelform_python
Version: 0.2.1
Summary: SkelForm runtime for Python
Author-email: Retropaint <darkglasses1122@gmail.com>
License-Expression: MIT
Classifier: Operating System :: OS Independent
Classifier: Programming Language :: Python :: 3
Requires-Python: >=3.9
